dash_ddx_catalog/__init__.py
dash_ddx_catalog/apps.py
dash_ddx_catalog/fields.py
dash_ddx_catalog/forms.py
dash_ddx_catalog/models.py
dash_ddx_catalog/migrations/__init__.py
dash_ddx_catalog/tests/__init__.py
dash_ddx_catalog/tests/test_simple.py
django_dash_ddx_catalog-0.1.3.dist-info/LICENSE
django_dash_ddx_catalog-0.1.3.dist-info/METADATA
django_dash_ddx_catalog-0.1.3.dist-info/WHEEL
django_dash_ddx_catalog-0.1.3.dist-info/top_level.txt
django_dash_ddx_catalog-0.1.3.dist-info/RECORD
