Metadata-Version: 2.1
Name: django-dash-ddx-catalog
Version: 0.1.3
Summary: Auxiliary Django forms for semi-automatic CRUD for dash-devextreme components
Home-page: https://github.com/pikhovkin/django-dash-ddx-catalog
Author: Sergei Pikhovkin
Author-email: s@pikhovkin.ru
License: MIT
Platform: UNKNOWN
Classifier: Development Status :: 3 - Alpha
Classifier: Environment :: Web Environment
Classifier: Framework :: Django :: 3.1
Classifier: Framework :: Django :: 3.2
Classifier: Intended Audience :: Developers
Classifier: License :: OSI Approved :: MIT License
Classifier: Operating System :: OS Independent
Classifier: Programming Language :: Python :: 3 :: Only
Classifier: Programming Language :: Python :: 3.7
Classifier: Programming Language :: Python :: 3.8
Classifier: Programming Language :: Python :: 3.9
Classifier: Programming Language :: Python :: 3.10
Requires-Python: >=3.7.*, <4.0.*
License-File: LICENSE
Requires-Dist: Django (<4.0,>=3.1)
Requires-Dist: dj-plotly-dash[all] (<0.19.0)
Requires-Dist: dash-devextreme
Requires-Dist: dash-core-components (<2.0.0)
Requires-Dist: dash-html-components (<2.0.0)
